{
	"id": "9fea1f56-a967-4009-97e3-3ac3cec583ef",
	"name": "BPR Localhost",
	"values": [
		{
			"key": "bpmServiceURL",
			"value": "localhost:8000",
			"enabled": true
		},
		{
			"key": "documentServiceURL",
			"value": "localhost:8001",
			"enabled": true
		},
		{
			"key": "notificationServiceURL",
			"value": "localhost:8002",
			"enabled": true
		},
		{
			"key": "userServiceURL",
			"value": "localhost:8003",
			"enabled": true
		},
		{
			"key": "certificateAuthorityURL",
			"value": "localhost:8004",
			"enabled": true
		},
		{
			"key": "deviceServiceURL",
			"value": "localhost:8005",
			"enabled": true
		},
		{
			"key": "uploadedDocumentId",
			"value": "",
			"enabled": true
		},
		{
			"key": "currentUserId",
			"value": "",
			"enabled": true
		},
		{
			"key": "registeredDevice",
			"value": "",
			"enabled": true
		}
	],
	"_postman_variable_scope": "environment",
	"_postman_exported_at": "2021-10-22T23:28:12.293Z",
	"_postman_exported_using": "Postman/8.12.4"
}