{"swagger":"2.0","info":{"description":"DESCRIPTION","version":"VERSION","title":"TITLE","termsOfService":"http://terms-of-services.url","license":{"name":"LICENSE","url":"http://url-to-license.com"}},"host":"localhost:8003","basePath":"/","tags":[{"name":"auth-controller","description":"Auth Controller"},{"name":"basic-error-controller","description":"Basic Error Controller"},{"name":"ping-controller","description":"Ping Controller"},{"name":"temp-controller","description":"Temp Controller"},{"name":"user-controller","description":"User Controller"}],"paths":{"/api/assignRole":{"post":{"tags":["user-controller"],"summary":"Assigns a role to the user","operationId":"assignRole","consumes":["application/json"],"produces":["*/*"],"parameters":[{"in":"body","name":"roleManagementRequest","description":"roleManagementRequest","required":true,"schema":{"$ref":"#/definitions/RoleManagementRequest"}}],"responses":{"200":{"description":"OK","schema":{"$ref":"#/definitions/BaseResponse"}},"201":{"description":"Created"},"401":{"description":"Unauthorized"},"403":{"description":"Forbidden"},"404":{"description":"Not Found"}}}},"/api/create":{"post":{"tags":["user-controller"],"summary":"Creates a user","operationId":"createUser","consumes":["application/json"],"produces":["*/*"],"parameters":[{"in":"body","name":"userCreateRequest","description":"userCreateRequest","required":true,"schema":{"$ref":"#/definitions/UserCreateRequest"}}],"responses":{"200":{"description":"OK","schema":{"$ref":"#/definitions/UserCreateResponse"}},"201":{"description":"Created"},"401":{"description":"Unauthorized"},"403":{"description":"Forbidden"},"404":{"description":"Not Found"}}}},"/api/getAvailableApprovers":{"post":{"tags":["user-controller"],"summary":"Get Available Approvers","operationId":"getAvailableApprovers","consumes":["application/json"],"produces":["*/*"],"responses":{"200":{"description":"OK","schema":{"type":"array","items":{"$ref":"#/definitions/User"}}},"201":{"description":"Created"},"401":{"description":"Unauthorized"},"403":{"description":"Forbidden"},"404":{"description":"Not Found"}}}},"/api/getAvailableRoles":{"post":{"tags":["user-controller"],"summary":"Returns available roles to be assigned","operationId":"getAvailableRoles","consumes":["application/json"],"produces":["*/*"],"responses":{"200":{"description":"OK","schema":{"type":"array","items":{"$ref":"#/definitions/SignfluentRoleResponse"}}},"201":{"description":"Created"},"401":{"description":"Unauthorized"},"403":{"description":"Forbidden"},"404":{"description":"Not Found"}}}},"/api/getRolesForCurrentUser":{"post":{"tags":["user-controller"],"summary":"Returns roles of specified user","operationId":"getRolesForCurrentUser","consumes":["application/json"],"produces":["*/*"],"responses":{"200":{"description":"OK","schema":{"type":"array","items":{"$ref":"#/definitions/SignfluentRoleResponse"}}},"201":{"description":"Created"},"401":{"description":"Unauthorized"},"403":{"description":"Forbidden"},"404":{"description":"Not Found"}}}},"/api/getRolesForUser":{"post":{"tags":["user-controller"],"summary":"Returns roles for specified user","operationId":"getRolesForUser","consumes":["application/json"],"produces":["*/*"],"parameters":[{"in":"body","name":"userRequest","description":"userRequest","required":true,"schema":{"$ref":"#/definitions/UserRequest"}}],"responses":{"200":{"description":"OK","schema":{"type":"array","items":{"$ref":"#/definitions/SignfluentRoleResponse"}}},"201":{"description":"Created"},"401":{"description":"Unauthorized"},"403":{"description":"Forbidden"},"404":{"description":"Not Found"}}}},"/api/revokeRole":{"post":{"tags":["user-controller"],"summary":"Removes a role from the user","operationId":"revokeRole","consumes":["application/json"],"produces":["*/*"],"parameters":[{"in":"body","name":"roleManagementRequest","description":"roleManagementRequest","required":true,"schema":{"$ref":"#/definitions/RoleManagementRequest"}}],"responses":{"200":{"description":"OK","schema":{"$ref":"#/definitions/BaseResponse"}},"201":{"description":"Created"},"401":{"description":"Unauthorized"},"403":{"description":"Forbidden"},"404":{"description":"Not Found"}}}},"/authenticate":{"post":{"tags":["auth-controller"],"summary":"Authenticate User","operationId":"authenticate","consumes":["application/json"],"produces":["*/*"],"parameters":[{"in":"body","name":"authenticationRequest","description":"authenticationRequest","required":true,"schema":{"$ref":"#/definitions/AuthenticationRequest"}}],"responses":{"200":{"description":"OK","schema":{"$ref":"#/definitions/AuthenticationResponse"}},"201":{"description":"Created"},"401":{"description":"Unauthorized"},"403":{"description":"Forbidden"},"404":{"description":"Not Found"}}}},"/error":{"get":{"tags":["basic-error-controller"],"summary":"errorHtml","operationId":"errorHtmlUsingGET","produces":["text/html"],"responses":{"200":{"description":"OK","schema":{"$ref":"#/definitions/ModelAndView"}},"401":{"description":"Unauthorized"},"403":{"description":"Forbidden"},"404":{"description":"Not Found"}}},"head":{"tags":["basic-error-controller"],"summary":"errorHtml","operationId":"errorHtmlUsingHEAD","consumes":["application/json"],"produces":["text/html"],"responses":{"200":{"description":"OK","schema":{"$ref":"#/definitions/ModelAndView"}},"204":{"description":"No Content"},"401":{"description":"Unauthorized"},"403":{"description":"Forbidden"}}},"post":{"tags":["basic-error-controller"],"summary":"errorHtml","operationId":"errorHtmlUsingPOST","consumes":["application/json"],"produces":["text/html"],"responses":{"200":{"description":"OK","schema":{"$ref":"#/definitions/ModelAndView"}},"201":{"description":"Created"},"401":{"description":"Unauthorized"},"403":{"description":"Forbidden"},"404":{"description":"Not Found"}}},"put":{"tags":["basic-error-controller"],"summary":"errorHtml","operationId":"errorHtmlUsingPUT","consumes":["application/json"],"produces":["text/html"],"responses":{"200":{"description":"OK","schema":{"$ref":"#/definitions/ModelAndView"}},"201":{"description":"Created"},"401":{"description":"Unauthorized"},"403":{"description":"Forbidden"},"404":{"description":"Not Found"}}},"delete":{"tags":["basic-error-controller"],"summary":"errorHtml","operationId":"errorHtmlUsingDELETE","produces":["text/html"],"responses":{"200":{"description":"OK","schema":{"$ref":"#/definitions/ModelAndView"}},"204":{"description":"No Content"},"401":{"description":"Unauthorized"},"403":{"description":"Forbidden"}}},"options":{"tags":["basic-error-controller"],"summary":"errorHtml","operationId":"errorHtmlUsingOPTIONS","consumes":["application/json"],"produces":["text/html"],"responses":{"200":{"description":"OK","schema":{"$ref":"#/definitions/ModelAndView"}},"204":{"description":"No Content"},"401":{"description":"Unauthorized"},"403":{"description":"Forbidden"}}},"patch":{"tags":["basic-error-controller"],"summary":"errorHtml","operationId":"errorHtmlUsingPATCH","consumes":["application/json"],"produces":["text/html"],"responses":{"200":{"description":"OK","schema":{"$ref":"#/definitions/ModelAndView"}},"204":{"description":"No Content"},"401":{"description":"Unauthorized"},"403":{"description":"Forbidden"}}}},"/ping":{"get":{"tags":["ping-controller"],"summary":"ping","operationId":"pingUsingGET","produces":["*/*"],"responses":{"200":{"description":"OK","schema":{"type":"string"}},"401":{"description":"Unauthorized"},"403":{"description":"Forbidden"},"404":{"description":"Not Found"}}}},"/temp/get":{"post":{"tags":["temp-controller"],"summary":"getSignatureRequestForUser","operationId":"getSignatureRequestForUserUsingPOST","consumes":["application/json"],"produces":["*/*"],"parameters":[{"in":"body","name":"userId","description":"userId","required":true,"schema":{"type":"string"}}],"responses":{"200":{"description":"OK","schema":{"$ref":"#/definitions/SignfluentSignatureRequest"}},"201":{"description":"Created"},"401":{"description":"Unauthorized"},"403":{"description":"Forbidden"},"404":{"description":"Not Found"}}}},"/temp/submit":{"post":{"tags":["temp-controller"],"summary":"submitSignature","operationId":"submitSignatureUsingPOST","consumes":["application/json"],"produces":["*/*"],"parameters":[{"in":"body","name":"signfluentSignature","description":"signfluentSignature","required":true,"schema":{"$ref":"#/definitions/SignfluentSignature"}}],"responses":{"200":{"description":"OK","schema":{"type":"string"}},"201":{"description":"Created"},"401":{"description":"Unauthorized"},"403":{"description":"Forbidden"},"404":{"description":"Not Found"}}}}},"definitions":{"AuthenticationRequest":{"type":"object","properties":{"password":{"type":"string"},"username":{"type":"string"}},"title":"AuthenticationRequest"},"AuthenticationResponse":{"type":"object","properties":{"expiresIn":{"type":"integer","format":"int64"},"idToken":{"type":"string"},"notBeforePolicy":{"type":"integer","format":"int32"},"refreshExpiresIn":{"type":"integer","format":"int64"},"refreshToken":{"type":"string"},"token":{"type":"string"},"tokenType":{"type":"string"},"userId":{"type":"string"}},"title":"AuthenticationResponse"},"BaseResponse":{"type":"object","properties":{"message":{"type":"string"},"successful":{"type":"boolean"}},"title":"BaseResponse"},"ModelAndView":{"type":"object","properties":{"empty":{"type":"boolean"},"model":{"type":"object"},"modelMap":{"type":"object","additionalProperties":{"type":"object"}},"reference":{"type":"boolean"},"status":{"type":"string","enum":["ACCEPTED","ALREADY_REPORTED","BAD_GATEWAY","BAD_REQUEST","BANDWIDTH_LIMIT_EXCEEDED","CHECKPOINT","CONFLICT","CONTINUE","CREATED","DESTINATION_LOCKED","EXPECTATION_FAILED","FAILED_DEPENDENCY","FORBIDDEN","FOUND","GATEWAY_TIMEOUT","GONE","HTTP_VERSION_NOT_SUPPORTED","IM_USED","INSUFFICIENT_SPACE_ON_RESOURCE","INSUFFICIENT_STORAGE","INTERNAL_SERVER_ERROR","I_AM_A_TEAPOT","LENGTH_REQUIRED","LOCKED","LOOP_DETECTED","METHOD_FAILURE","METHOD_NOT_ALLOWED","MOVED_PERMANENTLY","MOVED_TEMPORARILY","MULTIPLE_CHOICES","MULTI_STATUS","NETWORK_AUTHENTICATION_REQUIRED","NON_AUTHORITATIVE_INFORMATION","NOT_ACCEPTABLE","NOT_EXTENDED","NOT_FOUND","NOT_IMPLEMENTED","NOT_MODIFIED","NO_CONTENT","OK","PARTIAL_CONTENT","PAYLOAD_TOO_LARGE","PAYMENT_REQUIRED","PERMANENT_REDIRECT","PRECONDITION_FAILED","PRECONDITION_REQUIRED","PROCESSING","PROXY_AUTHENTICATION_REQUIRED","REQUESTED_RANGE_NOT_SATISFIABLE","REQUEST_ENTITY_TOO_LARGE","REQUEST_HEADER_FIELDS_TOO_LARGE","REQUEST_TIMEOUT","REQUEST_URI_TOO_LONG","RESET_CONTENT","SEE_OTHER","SERVICE_UNAVAILABLE","SWITCHING_PROTOCOLS","TEMPORARY_REDIRECT","TOO_EARLY","TOO_MANY_REQUESTS","UNAUTHORIZED","UNAVAILABLE_FOR_LEGAL_REASONS","UNPROCESSABLE_ENTITY","UNSUPPORTED_MEDIA_TYPE","UPGRADE_REQUIRED","URI_TOO_LONG","USE_PROXY","VARIANT_ALSO_NEGOTIATES"]},"view":{"$ref":"#/definitions/View"},"viewName":{"type":"string"}},"title":"ModelAndView"},"RoleManagementRequest":{"type":"object","properties":{"role":{"type":"string"},"userId":{"type":"string"}},"title":"RoleManagementRequest"},"SignfluentRoleResponse":{"type":"object","properties":{"key":{"type":"string"},"name":{"type":"string"}},"title":"SignfluentRoleResponse"},"SignfluentSignature":{"type":"object","properties":{"certificate":{"type":"string"},"signedHash":{"type":"string"},"taskId":{"type":"string"}},"title":"SignfluentSignature"},"SignfluentSignatureRequest":{"type":"object","properties":{"hash":{"type":"string"},"taskId":{"type":"string"}},"title":"SignfluentSignatureRequest"},"User":{"type":"object","properties":{"email":{"type":"string"},"firstName":{"type":"string"},"id":{"type":"string"},"lastName":{"type":"string"},"username":{"type":"string"}},"title":"User"},"UserCreateRequest":{"type":"object","properties":{"email":{"type":"string"},"firstName":{"type":"string"},"lastName":{"type":"string"},"password":{"type":"string"},"username":{"type":"string"}},"title":"UserCreateRequest"},"UserCreateResponse":{"type":"object","properties":{"userId":{"type":"string"}},"title":"UserCreateResponse"},"UserRequest":{"type":"object","properties":{"userId":{"type":"string"}},"title":"UserRequest"},"View":{"type":"object","properties":{"contentType":{"type":"string"}},"title":"View"}}}